stockscraper/__init__.py
stockscraper/stockscraper.py
stockscraper-0.1.1.dist-info/LICENSE
stockscraper-0.1.1.dist-info/METADATA
stockscraper-0.1.1.dist-info/WHEEL
stockscraper-0.1.1.dist-info/top_level.txt
stockscraper-0.1.1.dist-info/RECORD
