Metadata-Version: 2.1
Name: stockscraper
Version: 0.1.1
Summary: A Tool for collecting stock data, to do fundamental analysis and does not predict or recommend any stock in particular.
Home-page: https://github.com/pallav2905-py/stockscraper
Author: Pallav
Author-email: pallav.dev@outlook.com
License: MIT License
Project-URL: Bug Tracker, https://github.com/pallav2905-py/stockscraper/issues
Classifier: License :: OSI Approved :: MIT License
Classifier: Programming Language :: Python :: 3
Classifier: Operating System :: OS Independent
Requires-Python: >=3.6
License-File: LICENSE
Requires-Dist: tqdm >=4.64.1
Requires-Dist: beautifulsoup4 >=4.9.0
Requires-Dist: requests >=2.0.0
